odoo9_addon_website_snippet_country_dropdown-9.0.1.0.0.99.dev10-py2.7-nspkg.pth
odoo9_addon_website_snippet_country_dropdown-9.0.1.0.0.99.dev10.dist-info/DESCRIPTION.rst
odoo9_addon_website_snippet_country_dropdown-9.0.1.0.0.99.dev10.dist-info/METADATA
odoo9_addon_website_snippet_country_dropdown-9.0.1.0.0.99.dev10.dist-info/RECORD
odoo9_addon_website_snippet_country_dropdown-9.0.1.0.0.99.dev10.dist-info/WHEEL
odoo9_addon_website_snippet_country_dropdown-9.0.1.0.0.99.dev10.dist-info/metadata.json
odoo9_addon_website_snippet_country_dropdown-9.0.1.0.0.99.dev10.dist-info/namespace_packages.txt
odoo9_addon_website_snippet_country_dropdown-9.0.1.0.0.99.dev10.dist-info/top_level.txt
odoo_addons/website_snippet_country_dropdown/README.rst
odoo_addons/website_snippet_country_dropdown/__init__.py
odoo_addons/website_snippet_country_dropdown/__openerp__.py
odoo_addons/website_snippet_country_dropdown/demo/pages.xml
odoo_addons/website_snippet_country_dropdown/i18n/en.po
odoo_addons/website_snippet_country_dropdown/i18n/es.po
odoo_addons/website_snippet_country_dropdown/i18n/fr.po
odoo_addons/website_snippet_country_dropdown/i18n/pt_BR.po
odoo_addons/website_snippet_country_dropdown/i18n/sl.po
odoo_addons/website_snippet_country_dropdown/i18n/website_snippet_country_dropdown.pot
odoo_addons/website_snippet_country_dropdown/static/description/icon.png
odoo_addons/website_snippet_country_dropdown/static/src/css/style.sass
odoo_addons/website_snippet_country_dropdown/static/src/js/website_snippet_country_dropdown.editor.js
odoo_addons/website_snippet_country_dropdown/static/src/js/website_snippet_country_dropdown.js
odoo_addons/website_snippet_country_dropdown/static/src/xml/country_dropdown.xml
odoo_addons/website_snippet_country_dropdown/views/assets.xml
odoo_addons/website_snippet_country_dropdown/views/snippets.xml
